enumerate_markdown/__init__.py
enumerate_markdown/enumerate_markdown.py
enumerate_markdown/enumerator.py
enumerate_markdown/header.py
enumerate_markdown/headers_finder.py
enumerate_markdown-1.0.0.data/scripts/markdown-enum
enumerate_markdown-1.0.0.dist-info/LICENSE
enumerate_markdown-1.0.0.dist-info/METADATA
enumerate_markdown-1.0.0.dist-info/WHEEL
enumerate_markdown-1.0.0.dist-info/top_level.txt
enumerate_markdown-1.0.0.dist-info/RECORD
