Metadata-Version: 2.1
Name: enumerate-markdown
Version: 1.0.0
Summary: Enumerates your markdown headers, inside the md file
Home-page: https://github.com/a4vision/enumerate-markdown
Author: Assaf Yifrach
Author-email: asafyi@gmail.com
License: UNKNOWN
Platform: UNKNOWN
Classifier: Programming Language :: Python :: 3
Classifier: License :: OSI Approved :: MIT License
Classifier: Operating System :: OS Independent
License-File: LICENSE
Requires-Dist: mistune (>=2.0)
